transitle/__init__.py
transitle/__main__.py
transitle/translator.py
transitle/ts.py
transitle-1.1.0.dist-info/LICENSE
transitle-1.1.0.dist-info/METADATA
transitle-1.1.0.dist-info/WHEEL
transitle-1.1.0.dist-info/entry_points.txt
transitle-1.1.0.dist-info/top_level.txt
transitle-1.1.0.dist-info/RECORD
