Metadata-Version: 2.1
Name: transitle
Version: 1.1.0
Summary: AI-Based Subtitle translator. Translate subtitles in a folder flawlessly
Home-page: https://github.com/gunesmes/subtitle_translator
Author: Mesut Gunes
Author-email: gunesmes@gmail.com
License: LICENSE.md
Requires-Python: >=3.0
License-File: LICENSE
Requires-Dist: googletranslate-python
Requires-Dist: requests
